{
  "entity": "market",
  "market_id": "508005",
  "folder_rule": "market.createdAt (fallback: market.published_at)",
  "folder_dt_utc": "2024-09-24T19:19:16.884227Z",
  "market_createdAt": "2024-09-24T19:19:16.884227Z",
  "market_updatedAt": "2025-03-14T22:28:19.411684Z",
  "market_startDate": "2024-09-25T14:48:47.497219Z",
  "market_endDate": "2025-05-21T12:00:00Z",
  "market_closedTime": "2025-03-14 01:32:44+00",
  "conditionId": "0xc6798ad2863ce49e34e409bd5edaf0f4b34d591988f601bd3653d0a1797f5999",
  "slug": "will-real-sociedad-win-the-uefa-europa-league",
  "question": "Will Real Sociedad win the UEFA Europa League?"
}