{"active":true,"archived":false,"automaticallyActive":true,"automaticallyResolved":true,"closed":true,"closedTime":"2024-12-08T02:34:09Z","commentCount":9,"createdAt":"2024-10-23T00:02:09.093483Z","creationDate":"2024-10-23T18:01:29.97569Z","cumulativeMarkets":false,"cyom":false,"deploying":false,"description":"This is a market on predicting the winner of the Major League Soccer Cup.","enableNegRisk":true,"enableOrderBook":true,"endDate":"2024-12-07T12:00:00Z","featured":false,"gmpChartMode":"default","icon":"https://polymarket-upload.s3.us-east-2.amazonaws.com/mls-cup-winner-NCI7BblzI8Cl.png","id":"13704","image":"https://polymarket-upload.s3.us-east-2.amazonaws.com/mls-cup-winner-NCI7BblzI8Cl.png","markets":[{"acceptingOrders":false,"acceptingOrdersTimestamp":"2024-10-23T17:50:21Z","active":true,"approved":true,"archived":false,"automaticallyActive":true,"automaticallyResolved":true,"bestAsk":0.001,"clearBookOnStart":true,"clobRewards":[{"assetAddress":"0x2791Bca1f2de4661ED88A30C99A7a9449Aa84174","conditionId":"0x83d121ef18531a3e0c7f99650240bff60e7d4eac33d3cdc5873929c99e8ef49f","endDate":"2500-12-31","id":"9196","rewardsAmount":0,"rewardsDailyRate":5,"startDate":"2024-10-23"}],"clobTokenIds":"[\"28312968764608677212885560836025585200567354113492203970872299043623291174913\", \"81741518398221712163827469810764539843361363193582911246044025285817236263642\"]","closed":true,"closedTime":"2024-11-10 17:22:41+00","conditionId":"0x83d121ef18531a3e0c7f99650240bff60e7d4eac33d3cdc5873929c99e8ef49f","createdAt":"2024-10-23T00:06:35.41658Z","cyom":false,"deploying":false,"description":"This market will resolve to “Yes” if Inter Miami win the 2024 MLS Cup. Otherwise, this market will resolve to “No”.\n\nIf at any point it becomes impossible for this team to win the MLS Cup based on the rules of the MLS (e.g., they are eliminated in the playoff bracket), this market will resolve immediately to “No”.\n\nThe resolution source for this market will be information from the MLS.","enableOrderBook":true,"endDate":"2024-12-07T12:00:00Z","endDateIso":"2024-12-07","featured":false,"feesEnabled":false,"funded":false,"groupItemThreshold":"0","groupItemTitle":"Inter Miami","hasReviewedDates":true,"holdingRewardsEnabled":false,"icon":"https://polymarket-upload.s3.us-east-2.amazonaws.com/will-the-inter-miami-win-the-2024-mls-cup-KEXUhwa9JF-K.png","id":"510681","image":"https://polymarket-upload.s3.us-east-2.amazonaws.com/will-the-inter-miami-win-the-2024-mls-cup-KEXUhwa9JF-K.png","lastTradePrice":1,"manualActivation":false,"marketMakerAddress":"","negRisk":true,"negRiskMarketID":"0xd0558ff338582fd13f5a87a76983b6991e09f54106bd471a555bdc77151c9c00","negRiskOther":false,"negRiskRequestID":"0xcf7b84bf84b431a73bc9920a80caf2ea5caf881ed5f362a41ce866044f5641cb","new":false,"oneDayPriceChange":-0.4345,"oneHourPriceChange":0,"oneMonthPriceChange":0,"oneWeekPriceChange":0,"oneYearPriceChange":0,"orderMinSize":5,"orderPriceMinTickSize":0.001,"outcomePrices":"[\"0\", \"1\"]","outcomes":"[\"Yes\", \"No\"]","pagerDutyNotificationEnabled":false,"pendingDeployment":false,"question":"Will the Inter Miami win the 2024 MLS Cup?","questionID":"0xd0558ff338582fd13f5a87a76983b6991e09f54106bd471a555bdc77151c9c00","ready":false,"requiresTranslation":false,"resolutionSource":"","resolvedBy":"0x2F5e3684cb1F318ec51b00Edba38d79Ac2c0aA9d","restricted":true,"rewardsMaxSpread":3.5,"rewardsMinSize":50,"rfqEnabled":false,"seriesColor":"","showGmpOutcome":false,"showGmpSeries":false,"slug":"will-the-inter-miami-win-the-2024-mls-cup","spread":0.001,"startDate":"2024-10-23T17:51:29.718417Z","startDateIso":"2024-10-23","submitted_by":"0x91430CaD2d3975766499717fA0D66A78D814E5c5","umaBond":"500","umaEndDate":"2024-11-10T17:22:41Z","umaResolutionStatus":"resolved","umaResolutionStatuses":"[]","umaReward":"5","updatedAt":"2024-11-11T15:46:54.170187Z","volume":"47540.655203","volume1mo":0,"volume1moAmm":0,"volume1moClob":0,"volume1wk":0,"volume1wkAmm":0,"volume1wkClob":0,"volume1yr":0,"volume1yrAmm":0,"volume1yrClob":0,"volumeClob":47540.655203,"volumeNum":47540.655203},{"acceptingOrders":false,"acceptingOrdersTimestamp":"2024-10-23T17:50:41Z","active":true,"approved":true,"archived":false,"automaticallyActive":true,"automaticallyResolved":true,"bestAsk":1,"bestBid":0.999,"clearBookOnStart":true,"clobRewards":[{"assetAddress":"0x2791Bca1f2de4661ED88A30C99A7a9449Aa84174","conditionId":"0x88b2d0dbeefb1a24ceb4592f549c5770f769e36474d5c2b4804b679a0516ae6d","endDate":"2500-12-31","id":"9195","rewardsAmount":0,"rewardsDailyRate":30,"startDate":"2024-10-23"}],"clobTokenIds":"[\"68039806196763778072426677927765602446949408355135170386644449937755396575589\", \"5807247258482043452854602908688324706643683895590608347253213824819918655436\"]","closed":true,"closedTime":"2024-12-08 02:24:22+00","conditionId":"0x88b2d0dbeefb1a24ceb4592f549c5770f769e36474d5c2b4804b679a0516ae6d","createdAt":"2024-10-23T00:08:52.805791Z","cyom":false,"deploying":false,"description":"This market will resolve to “Yes” if the LA Galaxy win the 2024 MLS Cup. Otherwise, this market will resolve to “No”.\n\nIf at any point it becomes impossible for this team to win the MLS Cup based on the rules of the MLS (e.g., they are eliminated in the playoff bracket), this market will resolve immediately to “No”.\n\nThe resolution source for this market will be information from the MLS.","enableOrderBook":true,"endDate":"2024-12-07T12:00:00Z","endDateIso":"2024-12-07","featured":false,"feesEnabled":false,"funded":false,"groupItemThreshold":"1","groupItemTitle":"LA Galaxy","hasReviewedDates":true,"holdingRewardsEnabled":false,"icon":"https://polymarket-upload.s3.us-east-2.amazonaws.com/will-la-galaxy-win-the-mls-cup-76ShAVjfU369.png","id":"510682","image":"https://polymarket-upload.s3.us-east-2.amazonaws.com/will-la-galaxy-win-the-mls-cup-76ShAVjfU369.png","lastTradePrice":1,"manualActivation":false,"marketMakerAddress":"","negRisk":true,"negRiskMarketID":"0xd0558ff338582fd13f5a87a76983b6991e09f54106bd471a555bdc77151c9c00","negRiskOther":false,"negRiskRequestID":"0xfaedec9ff129271332cf8cf590a7fe5f68b436d1599c122b0149d0a9e77469db","new":false,"oneDayPriceChange":0.3295,"oneHourPriceChange":0,"oneMonthPriceChange":0,"oneWeekPriceChange":0,"oneYearPriceChange":0,"orderMinSize":5,"orderPriceMinTickSize":0.001,"outcomePrices":"[\"1\", \"0\"]","outcomes":"[\"Yes\", \"No\"]","pagerDutyNotificationEnabled":false,"pendingDeployment":false,"question":"Will LA Galaxy win the MLS Cup?","questionID":"0xd0558ff338582fd13f5a87a76983b6991e09f54106bd471a555bdc77151c9c01","ready":false,"requiresTranslation":false,"resolutionSource":"","resolvedBy":"0x2F5e3684cb1F318ec51b00Edba38d79Ac2c0aA9d","restricted":true,"rewardsMaxSpread":3.5,"rewardsMinSize":50,"rfqEnabled":false,"seriesColor":"","showGmpOutcome":false,"showGmpSeries":false,"slug":"will-la-galaxy-win-the-mls-cup","spread":0.001,"startDate":"2024-10-23T17:51:52.906072Z","startDateIso":"2024-10-23","submitted_by":"0x91430CaD2d3975766499717fA0D66A78D814E5c5","umaBond":"500","umaEndDate":"2024-12-08T02:24:22Z","umaResolutionStatus":"resolved","umaResolutionStatuses":"[]","umaReward":"5","updatedAt":"2024-12-09T00:51:26.712926Z","volume":"8737.484983","volume1mo":0,"volume1moAmm":0,"volume1moClob":0,"volume1wk":0,"volume1wkAmm":0,"volume1wkClob":0,"volume1yr":0,"volume1yrAmm":0,"volume1yrClob":0,"volumeClob":8737.484983,"volumeNum":8737.484983},{"acceptingOrders":false,"acceptingOrdersTimestamp":"2024-10-23T17:51:05Z","active":true,"approved":true,"archived":false,"automaticallyActive":true,"automaticallyResolved":true,"bestAsk":0.001,"clearBookOnStart":true,"clobRewards":[{"assetAddress":"0x2791Bca1f2de4661ED88A30C99A7a9449Aa84174","conditionId":"0xbf90b5982b6aff220c96c46d8ab5472440349525021e7d7aaf985bc122994855","endDate":"2500-12-31","id":"9194","rewardsAmount":0,"rewardsDailyRate":5,"startDate":"2024-10-23"}],"clobTokenIds":"[\"83727028263168489809274932483674161444560204362713755576312029095960489430821\", \"43948969910673448336366091955825604409155038188458383437600266868209911752953\"]","closed":true,"closedTime":"2024-11-10 20:23:09+00","conditionId":"0xbf90b5982b6aff220c96c46d8ab5472440349525021e7d7aaf985bc122994855","createdAt":"2024-10-23T00:11:33.274161Z","cyom":false,"deploying":false,"description":"This market will resolve to “Yes” if the Columbus Crew win the 2024 MLS Cup. Otherwise, this market will resolve to “No”.\n\nIf at any point it becomes impossible for this team to win the MLS Cup based on the rules of the MLS (e.g., they are eliminated in the playoff bracket), this market will resolve immediately to “No”.\n\nThe resolution source for this market will be information from the MLS.","enableOrderBook":true,"endDate":"2024-12-07T12:00:00Z","endDateIso":"2024-12-07","featured":false,"feesEnabled":false,"funded":false,"groupItemThreshold":"2","groupItemTitle":"Columbus Crew","hasReviewedDates":true,"holdingRewardsEnabled":false,"icon":"https://polymarket-upload.s3.us-east-2.amazonaws.com/will-columbus-crew-win-the-mls-cup-TbOCztA8Gf2T.png","id":"510683","image":"https://polymarket-upload.s3.us-east-2.amazonaws.com/will-columbus-crew-win-the-mls-cup-TbOCztA8Gf2T.png","lastTradePrice":1,"manualActivation":false,"marketMakerAddress":"","negRisk":true,"negRiskMarketID":"0xd0558ff338582fd13f5a87a76983b6991e09f54106bd471a555bdc77151c9c00","negRiskOther":false,"negRiskRequestID":"0x23ab30f26137fcaf9b8c46c8ca8362557fb8b6746a975ca0d5cccac83d48bb85","new":false,"oneDayPriceChange":-0.002,"oneHourPriceChange":0,"oneMonthPriceChange":0,"oneWeekPriceChange":0,"oneYearPriceChange":0,"orderMinSize":5,"orderPriceMinTickSize":0.001,"outcomePrices":"[\"0\", \"1\"]","outcomes":"[\"Yes\", \"No\"]","pagerDutyNotificationEnabled":false,"pendingDeployment":false,"question":"Will Columbus Crew win the MLS Cup?","questionID":"0xd0558ff338582fd13f5a87a76983b6991e09f54106bd471a555bdc77151c9c02","ready":false,"requiresTranslation":false,"resolutionSource":"","resolvedBy":"0x2F5e3684cb1F318ec51b00Edba38d79Ac2c0aA9d","restricted":true,"rewardsMaxSpread":3.5,"rewardsMinSize":50,"rfqEnabled":false,"seriesColor":"","showGmpOutcome":false,"showGmpSeries":false,"slug":"will-columbus-crew-win-the-mls-cup","spread":0.001,"startDate":"2024-10-23T17:52:18.660874Z","startDateIso":"2024-10-23","submitted_by":"0x91430CaD2d3975766499717fA0D66A78D814E5c5","umaBond":"500","umaEndDate":"2024-11-10T20:23:09Z","umaResolutionStatus":"resolved","umaResolutionStatuses":"[]","umaReward":"5","updatedAt":"2024-11-11T18:53:15.793642Z","volume":"330038.051967","volume1mo":0,"volume1moAmm":0,"volume1moClob":0,"volume1wk":0,"volume1wkAmm":0,"volume1wkClob":0,"volume1yr":0,"volume1yrAmm":0,"volume1yrClob":0,"volumeClob":330038.051967,"volumeNum":330038.051967},{"acceptingOrders":false,"acceptingOrdersTimestamp":"2024-10-23T17:51:35Z","active":true,"approved":true,"archived":false,"automaticallyActive":true,"automaticallyResolved":true,"bestAsk":0.001,"clearBookOnStart":true,"clobRewards":[{"assetAddress":"0x2791Bca1f2de4661ED88A30C99A7a9449Aa84174","conditionId":"0x0ae555df599a757ef51ad4d1adf2d7c337b1ff81eca8a1ed8e04e7901d8a9cec","endDate":"2500-12-31","id":"9193","rewardsAmount":0,"rewardsDailyRate":5,"startDate":"2024-10-23"}],"clobTokenIds":"[\"39007476913468606059888960207364075081327139130117962733257673812735106842803\", \"26939375676660500503106417015593271336398753917064742535603154001585756882568\"]","closed":true,"closedTime":"2024-11-24 09:35:41+00","conditionId":"0x0ae555df599a757ef51ad4d1adf2d7c337b1ff81eca8a1ed8e04e7901d8a9cec","createdAt":"2024-10-23T00:11:33.71313Z","cyom":false,"deploying":false,"description":"This market will resolve to “Yes” if Los Angeles FC win the 2024 MLS Cup. Otherwise, this market will resolve to “No”.\n\nIf at any point it becomes impossible for this team to win the MLS Cup based on the rules of the MLS (e.g., they are eliminated in the playoff bracket), this market will resolve immediately to “No”.\n\nThe resolution source for this market will be information from the MLS.","enableOrderBook":true,"endDate":"2024-12-07T12:00:00Z","endDateIso":"2024-12-07","featured":false,"feesEnabled":false,"funded":false,"groupItemThreshold":"3","groupItemTitle":"Los Angeles FC","hasReviewedDates":true,"holdingRewardsEnabled":false,"icon":"https://polymarket-upload.s3.us-east-2.amazonaws.com/will-los-angeles-fc-win-the-mls-cup-I5PivhyybYNT.png","id":"510684","image":"https://polymarket-upload.s3.us-east-2.amazonaws.com/will-los-angeles-fc-win-the-mls-cup-I5PivhyybYNT.png","lastTradePrice":1,"manualActivation":false,"marketMakerAddress":"","negRisk":true,"negRiskMarketID":"0xd0558ff338582fd13f5a87a76983b6991e09f54106bd471a555bdc77151c9c00","negRiskOther":false,"negRiskRequestID":"0x3d27a08cfe013da12f2e5d26789d776efbf7a8dbb97a089741d4e9af184679af","new":false,"oneDayPriceChange":-0.2945,"oneHourPriceChange":0,"oneMonthPriceChange":0,"oneWeekPriceChange":0,"oneYearPriceChange":0,"orderMinSize":5,"orderPriceMinTickSize":0.001,"outcomePrices":"[\"0\", \"1\"]","outcomes":"[\"Yes\", \"No\"]","pagerDutyNotificationEnabled":false,"pendingDeployment":false,"question":"Will Los Angeles FC win the MLS Cup?","questionID":"0xd0558ff338582fd13f5a87a76983b6991e09f54106bd471a555bdc77151c9c03","ready":false,"requiresTranslation":false,"resolutionSource":"","resolvedBy":"0x2F5e3684cb1F318ec51b00Edba38d79Ac2c0aA9d","restricted":true,"rewardsMaxSpread":3.5,"rewardsMinSize":50,"rfqEnabled":false,"seriesColor":"","showGmpOutcome":false,"showGmpSeries":false,"slug":"will-los-angeles-fc-win-the-mls-cup","spread":0.001,"startDate":"2024-10-23T17:52:44.854483Z","startDateIso":"2024-10-23","submitted_by":"0x91430CaD2d3975766499717fA0D66A78D814E5c5","umaBond":"500","umaEndDate":"2024-11-24T09:35:41Z","umaResolutionStatus":"resolved","umaResolutionStatuses":"[]","umaReward":"5","updatedAt":"2024-11-25T06:38:03.607262Z","volume":"8056.042837","volume1mo":0,"volume1moAmm":0,"volume1moClob":0,"volume1wk":0,"volume1wkAmm":0,"volume1wkClob":0,"volume1yr":0,"volume1yrAmm":0,"volume1yrClob":0,"volumeClob":8056.042837,"volumeNum":8056.042837},{"acceptingOrders":false,"acceptingOrdersTimestamp":"2024-10-23T17:51:59Z","active":true,"approved":true,"archived":false,"automaticallyActive":true,"automaticallyResolved":true,"bestAsk":0.1,"clearBookOnStart":true,"clobRewards":[{"assetAddress":"0x2791Bca1f2de4661ED88A30C99A7a9449Aa84174","conditionId":"0xcc4f953a3576b2c3d464262f5138e2f2ab66f7b052afc910f48aa63f811872d4","endDate":"2500-12-31","id":"9192","rewardsAmount":0,"rewardsDailyRate":5,"startDate":"2024-10-23"}],"clobTokenIds":"[\"113075792015824507839362248951676955735354568840181076532296665296941301614545\", \"98158439419236452603388164904161022776513588895315465592552436934601572195355\"]","closed":true,"closedTime":"2024-12-01 08:45:02+00","conditionId":"0xcc4f953a3576b2c3d464262f5138e2f2ab66f7b052afc910f48aa63f811872d4","createdAt":"2024-10-23T00:13:49.324883Z","cyom":false,"deploying":false,"description":"This market will resolve to “Yes” if the Seattle Sounders win the 2024 MLS Cup. Otherwise, this market will resolve to “No”.\n\nIf at any point it becomes impossible for this team to win the MLS Cup based on the rules of the MLS (e.g., they are eliminated in the playoff bracket), this market will resolve immediately to “No”.\n\nThe resolution source for this market will be information from the MLS.","enableOrderBook":true,"endDate":"2024-12-07T12:00:00Z","endDateIso":"2024-12-07","featured":false,"feesEnabled":false,"funded":false,"groupItemThreshold":"4","groupItemTitle":"Seattle Sounders","hasReviewedDates":true,"holdingRewardsEnabled":false,"icon":"https://polymarket-upload.s3.us-east-2.amazonaws.com/will-seattle-sounders-win-the-mls-cup-1dyHW52TN26l.png","id":"510685","image":"https://polymarket-upload.s3.us-east-2.amazonaws.com/will-seattle-sounders-win-the-mls-cup-1dyHW52TN26l.png","lastTradePrice":1,"manualActivation":false,"marketMakerAddress":"","negRisk":true,"negRiskMarketID":"0xd0558ff338582fd13f5a87a76983b6991e09f54106bd471a555bdc77151c9c00","negRiskOther":false,"negRiskRequestID":"0x80b0a4d1968a9be64ca0af754cbbe996c15e7ed248e7efd75079e452babe4e1f","new":false,"oneDayPriceChange":-0.11,"oneHourPriceChange":0,"oneMonthPriceChange":0,"oneWeekPriceChange":0,"oneYearPriceChange":0,"orderMinSize":5,"orderPriceMinTickSize":0.01,"outcomePrices":"[\"0\", \"1\"]","outcomes":"[\"Yes\", \"No\"]","pagerDutyNotificationEnabled":false,"pendingDeployment":false,"question":"Will the Seattle Sounders win the MLS Cup?","questionID":"0xd0558ff338582fd13f5a87a76983b6991e09f54106bd471a555bdc77151c9c04","ready":false,"requiresTranslation":false,"resolutionSource":"","resolvedBy":"0x2F5e3684cb1F318ec51b00Edba38d79Ac2c0aA9d","restricted":true,"rewardsMaxSpread":3.5,"rewardsMinSize":50,"rfqEnabled":false,"seriesColor":"","showGmpOutcome":false,"showGmpSeries":false,"slug":"will-seattle-sounders-win-the-mls-cup","spread":0.1,"startDate":"2024-10-23T17:53:11.352371Z","startDateIso":"2024-10-23","submitted_by":"0x91430CaD2d3975766499717fA0D66A78D814E5c5","umaBond":"500","umaEndDate":"2024-12-01T08:45:02Z","umaResolutionStatus":"resolved","umaResolutionStatuses":"[]","umaReward":"5","updatedAt":"2024-12-02T05:07:16.985307Z","volume":"6167.270771","volume1mo":0,"volume1moAmm":0,"volume1moClob":0,"volume1wk":0,"volume1wkAmm":0,"volume1wkClob":0,"volume1yr":0,"volume1yrAmm":0,"volume1yrClob":0,"volumeClob":6167.270771,"volumeNum":6167.270771},{"acceptingOrders":false,"acceptingOrdersTimestamp":"2024-10-23T17:52:31Z","active":true,"approved":true,"archived":false,"automaticallyActive":true,"automaticallyResolved":true,"bestAsk":0.005,"clearBookOnStart":true,"clobRewards":[{"assetAddress":"0x2791Bca1f2de4661ED88A30C99A7a9449Aa84174","conditionId":"0x0f8cb9b6de30300633d0bb4289af04afd296357d6ad46083beb0280e65e6280a","endDate":"2500-12-31","id":"9191","rewardsAmount":0,"rewardsDailyRate":5,"startDate":"2024-10-23"}],"clobTokenIds":"[\"76741157361861996655734937255256038073204285892130338868173988787448900221718\", \"68327098622559622035456689313918094530959240195229676837892950927408701315120\"]","closed":true,"closedTime":"2024-11-10 20:08:12+00","conditionId":"0x0f8cb9b6de30300633d0bb4289af04afd296357d6ad46083beb0280e65e6280a","createdAt":"2024-10-23T00:14:10.426132Z","cyom":false,"deploying":false,"description":"This market will resolve to “Yes” if FC Cincinnati win the 2024 MLS Cup. Otherwise, this market will resolve to “No”.\n\nIf at any point it becomes impossible for this team to win the MLS Cup based on the rules of the MLS (e.g., they are eliminated in the playoff bracket), this market will resolve immediately to “No”.\n\nThe resolution source for this market will be information from the MLS.","enableOrderBook":true,"endDate":"2024-12-07T12:00:00Z","endDateIso":"2024-12-07","featured":false,"feesEnabled":false,"funded":false,"groupItemThreshold":"5","groupItemTitle":"FC Cincinnati","hasReviewedDates":true,"holdingRewardsEnabled":false,"icon":"https://polymarket-upload.s3.us-east-2.amazonaws.com/will-fc-cincinnati-win-the-mls-cup-hVkeyGIT9vAm.png","id":"510686","image":"https://polymarket-upload.s3.us-east-2.amazonaws.com/will-fc-cincinnati-win-the-mls-cup-hVkeyGIT9vAm.png","lastTradePrice":1,"manualActivation":false,"marketMakerAddress":"","negRisk":true,"negRiskMarketID":"0xd0558ff338582fd13f5a87a76983b6991e09f54106bd471a555bdc77151c9c00","negRiskOther":false,"negRiskRequestID":"0x5cb39fece30fd600239f12b5dff9d146a1a601b5f6ebb33981e97eb6a0a3390c","new":false,"oneDayPriceChange":-0.0725,"oneHourPriceChange":0,"oneMonthPriceChange":0,"oneWeekPriceChange":0,"oneYearPriceChange":0,"orderMinSize":5,"orderPriceMinTickSize":0.001,"outcomePrices":"[\"0\", \"1\"]","outcomes":"[\"Yes\", \"No\"]","pagerDutyNotificationEnabled":false,"pendingDeployment":false,"question":"Will FC Cincinnati win the MLS Cup?","questionID":"0xd0558ff338582fd13f5a87a76983b6991e09f54106bd471a555bdc77151c9c05","ready":false,"requiresTranslation":false,"resolutionSource":"","resolvedBy":"0x2F5e3684cb1F318ec51b00Edba38d79Ac2c0aA9d","restricted":true,"rewardsMaxSpread":3.5,"rewardsMinSize":50,"rfqEnabled":false,"seriesColor":"","showGmpOutcome":false,"showGmpSeries":false,"slug":"will-fc-cincinnati-win-the-mls-cup","spread":0.005,"startDate":"2024-10-23T17:53:41.726077Z","startDateIso":"2024-10-23","submitted_by":"0x91430CaD2d3975766499717fA0D66A78D814E5c5","umaBond":"500","umaEndDate":"2024-11-10T20:08:12Z","umaResolutionStatus":"resolved","umaResolutionStatuses":"[]","umaReward":"5","updatedAt":"2024-11-11T16:22:40.25871Z","volume":"3987.854866","volume1mo":0,"volume1moAmm":0,"volume1moClob":0,"volume1wk":0,"volume1wkAmm":0,"volume1wkClob":0,"volume1yr":0,"volume1yrAmm":0,"volume1yrClob":0,"volumeClob":3987.854866,"volumeNum":3987.854866},{"acceptingOrders":false,"acceptingOrdersTimestamp":"2024-10-23T17:52:45Z","active":true,"approved":true,"archived":false,"automaticallyActive":true,"automaticallyResolved":true,"bestAsk":0.001,"clearBookOnStart":true,"clobRewards":[{"assetAddress":"0x2791Bca1f2de4661ED88A30C99A7a9449Aa84174","conditionId":"0x496f6ef3103ff2adbc13c611764b4c6ebd161f776d06f884de1c5dafdd7d1471","endDate":"2500-12-31","id":"9190","rewardsAmount":0,"rewardsDailyRate":5,"startDate":"2024-10-23"}],"clobTokenIds":"[\"80065300606233128847089076651224575550994201026596815996975552567572469941976\", \"17665234530335555981308962308566729171509780891049742487392783840306614588739\"]","closed":true,"closedTime":"2024-11-10 20:08:06+00","conditionId":"0x496f6ef3103ff2adbc13c611764b4c6ebd161f776d06f884de1c5dafdd7d1471","createdAt":"2024-10-23T00:14:29.384994Z","cyom":false,"deploying":false,"description":"This market will resolve to “Yes” if Real Salt Lake win the 2024 MLS Cup. Otherwise, this market will resolve to “No”.\n\nIf at any point it becomes impossible for this team to win the MLS Cup based on the rules of the MLS (e.g., they are eliminated in the playoff bracket), this market will resolve immediately to “No”.\n\nThe resolution source for this market will be information from the MLS.","enableOrderBook":true,"endDate":"2024-12-07T12:00:00Z","endDateIso":"2024-12-07","featured":false,"feesEnabled":false,"funded":false,"groupItemThreshold":"6","groupItemTitle":"Real Salt Lake","hasReviewedDates":true,"holdingRewardsEnabled":false,"icon":"https://polymarket-upload.s3.us-east-2.amazonaws.com/will-real-salt-lake-win-the-mls-cup-xRol2Ndq314T.png","id":"510687","image":"https://polymarket-upload.s3.us-east-2.amazonaws.com/will-real-salt-lake-win-the-mls-cup-xRol2Ndq314T.png","lastTradePrice":1,"manualActivation":false,"marketMakerAddress":"","negRisk":true,"negRiskMarketID":"0xd0558ff338582fd13f5a87a76983b6991e09f54106bd471a555bdc77151c9c00","negRiskOther":false,"negRiskRequestID":"0x9f3a99ee49d51e8f51824a0afb16b324b31684a71fdf751e99cae812c31d18cc","new":false,"oneDayPriceChange":-0.003,"oneHourPriceChange":0,"oneMonthPriceChange":0,"oneWeekPriceChange":0,"oneYearPriceChange":0,"orderMinSize":5,"orderPriceMinTickSize":0.001,"outcomePrices":"[\"0\", \"1\"]","outcomes":"[\"Yes\", \"No\"]","pagerDutyNotificationEnabled":false,"pendingDeployment":false,"question":"Will Real Salt Lake win the MLS Cup?","questionID":"0xd0558ff338582fd13f5a87a76983b6991e09f54106bd471a555bdc77151c9c06","ready":false,"requiresTranslation":false,"resolutionSource":"","resolvedBy":"0x2F5e3684cb1F318ec51b00Edba38d79Ac2c0aA9d","restricted":true,"rewardsMaxSpread":3.5,"rewardsMinSize":50,"rfqEnabled":false,"seriesColor":"","showGmpOutcome":false,"showGmpSeries":false,"slug":"will-real-salt-lake-win-the-mls-cup","spread":0.001,"startDate":"2024-10-23T17:53:53.595365Z","startDateIso":"2024-10-23","submitted_by":"0x91430CaD2d3975766499717fA0D66A78D814E5c5","umaBond":"500","umaEndDate":"2024-11-10T20:08:06Z","umaResolutionStatus":"resolved","umaResolutionStatuses":"[]","umaReward":"5","updatedAt":"2024-11-11T18:09:05.585055Z","volume":"323814.632","volume1mo":0,"volume1moAmm":0,"volume1moClob":0,"volume1wk":0,"volume1wkAmm":0,"volume1wkClob":0,"volume1yr":0,"volume1yrAmm":0,"volume1yrClob":0,"volumeClob":323814.632,"volumeNum":323814.632},{"acceptingOrders":false,"acceptingOrdersTimestamp":"2024-10-23T17:53:17Z","active":true,"approved":true,"archived":false,"automaticallyActive":true,"automaticallyResolved":true,"bestAsk":0.001,"clearBookOnStart":true,"clobRewards":[{"assetAddress":"0x2791Bca1f2de4661ED88A30C99A7a9449Aa84174","conditionId":"0xb3566ca4be424e359cc36e2cf5ea069b5bf392461305a871b7a6e4b12996dd8a","endDate":"2500-12-31","id":"9189","rewardsAmount":0,"rewardsDailyRate":5,"startDate":"2024-10-23"}],"clobTokenIds":"[\"26068938442089533946579427918548304194898127243705670593220710522113615280818\", \"9704407713673381415120390434323796952985898267877510025303601582462345621613\"]","closed":true,"closedTime":"2024-11-10 20:12:56+00","conditionId":"0xb3566ca4be424e359cc36e2cf5ea069b5bf392461305a871b7a6e4b12996dd8a","createdAt":"2024-10-23T00:15:12.312339Z","cyom":false,"deploying":false,"description":"This market will resolve to “Yes” if the Houston Dynamo win the 2024 MLS Cup. Otherwise, this market will resolve to “No”.\n\nIf at any point it becomes impossible for this team to win the MLS Cup based on the rules of the MLS (e.g., they are eliminated in the playoff bracket), this market will resolve immediately to “No”.\n\nThe resolution source for this market will be information from the MLS.","enableOrderBook":true,"endDate":"2024-12-07T12:00:00Z","endDateIso":"2024-12-07","featured":false,"feesEnabled":false,"funded":false,"groupItemThreshold":"7","groupItemTitle":"Houston Dynamo","hasReviewedDates":true,"holdingRewardsEnabled":false,"icon":"https://polymarket-upload.s3.us-east-2.amazonaws.com/will-houston-dynamo-win-the-mls-cup-EAibyKDveHIf.png","id":"510688","image":"https://polymarket-upload.s3.us-east-2.amazonaws.com/will-houston-dynamo-win-the-mls-cup-EAibyKDveHIf.png","lastTradePrice":1,"manualActivation":false,"marketMakerAddress":"","negRisk":true,"negRiskMarketID":"0xd0558ff338582fd13f5a87a76983b6991e09f54106bd471a555bdc77151c9c00","negRiskOther":false,"negRiskRequestID":"0x454294999188d2e6de913c221badd99fd792ab75e833adf06013e7bb7a63a676","new":false,"oneDayPriceChange":-0.002,"oneHourPriceChange":0,"oneMonthPriceChange":0,"oneWeekPriceChange":0,"oneYearPriceChange":0,"orderMinSize":5,"orderPriceMinTickSize":0.001,"outcomePrices":"[\"0\", \"1\"]","outcomes":"[\"Yes\", \"No\"]","pagerDutyNotificationEnabled":false,"pendingDeployment":false,"question":"Will the Houston Dynamo win the MLS Cup?","questionID":"0xd0558ff338582fd13f5a87a76983b6991e09f54106bd471a555bdc77151c9c07","ready":false,"requiresTranslation":false,"resolutionSource":"","resolvedBy":"0x2F5e3684cb1F318ec51b00Edba38d79Ac2c0aA9d","restricted":true,"rewardsMaxSpread":3.5,"rewardsMinSize":50,"rfqEnabled":false,"seriesColor":"","showGmpOutcome":false,"showGmpSeries":false,"slug":"will-houston-dynamo-win-the-mls-cup","spread":0.001,"startDate":"2024-10-23T17:54:29.149367Z","startDateIso":"2024-10-23","submitted_by":"0x91430CaD2d3975766499717fA0D66A78D814E5c5","umaBond":"500","umaEndDate":"2024-11-10T20:12:56Z","umaResolutionStatus":"resolved","umaResolutionStatuses":"[]","umaReward":"5","updatedAt":"2024-11-11T18:02:50.826942Z","volume":"319525.755214","volume1mo":0,"volume1moAmm":0,"volume1moClob":0,"volume1wk":0,"volume1wkAmm":0,"volume1wkClob":0,"volume1yr":0,"volume1yrAmm":0,"volume1yrClob":0,"volumeClob":319525.755214,"volumeNum":319525.755214},{"acceptingOrders":false,"acceptingOrdersTimestamp":"2024-10-23T17:53:31Z","active":true,"approved":true,"archived":false,"automaticallyActive":true,"automaticallyResolved":true,"bestAsk":0.001,"clearBookOnStart":true,"clobRewards":[{"assetAddress":"0x2791Bca1f2de4661ED88A30C99A7a9449Aa84174","conditionId":"0x474a6d6c61302fe4c2466c6f77b82b474c2cfd310751c6aa8f1b6e600113c48c","endDate":"2500-12-31","id":"9188","rewardsAmount":0,"rewardsDailyRate":5,"startDate":"2024-10-23"}],"clobTokenIds":"[\"56635995354743403389340953487468938059781755283306511877278530603836346245654\", \"16627171240321346947626379072960157237140936112093882762467607857509385443558\"]","closed":true,"closedTime":"2024-12-01 05:54:07+00","conditionId":"0x474a6d6c61302fe4c2466c6f77b82b474c2cfd310751c6aa8f1b6e600113c48c","createdAt":"2024-10-23T00:15:12.645412Z","cyom":false,"deploying":false,"description":"This market will resolve to “Yes” if Orlando City win the 2024 MLS Cup. Otherwise, this market will resolve to “No”.\n\nIf at any point it becomes impossible for this team to win the MLS Cup based on the rules of the MLS (e.g., they are eliminated in the playoff bracket), this market will resolve immediately to “No”.\n\nThe resolution source for this market will be information from the MLS.","enableOrderBook":true,"endDate":"2024-12-07T12:00:00Z","endDateIso":"2024-12-07","featured":false,"feesEnabled":false,"funded":false,"groupItemThreshold":"8","groupItemTitle":"Orlando City","hasReviewedDates":true,"holdingRewardsEnabled":false,"icon":"https://polymarket-upload.s3.us-east-2.amazonaws.com/will-orlando-city-win-the-mls-cup-sKUvE-0DGMar.png","id":"510689","image":"https://polymarket-upload.s3.us-east-2.amazonaws.com/will-orlando-city-win-the-mls-cup-sKUvE-0DGMar.png","lastTradePrice":1,"manualActivation":false,"marketMakerAddress":"","negRisk":true,"negRiskMarketID":"0xd0558ff338582fd13f5a87a76983b6991e09f54106bd471a555bdc77151c9c00","negRiskOther":false,"negRiskRequestID":"0x15ec59ede71de52e87ca9b97d6ac843a211413af159b87e2a5b0d38494958eba","new":false,"oneDayPriceChange":-0.3045,"oneHourPriceChange":0,"oneMonthPriceChange":0,"oneWeekPriceChange":0,"oneYearPriceChange":0,"orderMinSize":5,"orderPriceMinTickSize":0.001,"outcomePrices":"[\"0\", \"1\"]","outcomes":"[\"Yes\", \"No\"]","pagerDutyNotificationEnabled":false,"pendingDeployment":false,"question":"Will Orlando City win the MLS Cup?","questionID":"0xd0558ff338582fd13f5a87a76983b6991e09f54106bd471a555bdc77151c9c08","ready":false,"requiresTranslation":false,"resolutionSource":"","resolvedBy":"0x2F5e3684cb1F318ec51b00Edba38d79Ac2c0aA9d","restricted":true,"rewardsMaxSpread":3.5,"rewardsMinSize":50,"rfqEnabled":false,"seriesColor":"","showGmpOutcome":false,"showGmpSeries":false,"slug":"will-orlando-city-win-the-mls-cup","spread":0.001,"startDate":"2024-10-23T17:54:40.120879Z","startDateIso":"2024-10-23","submitted_by":"0x91430CaD2d3975766499717fA0D66A78D814E5c5","umaBond":"500","umaEndDate":"2024-12-01T05:54:07Z","umaResolutionStatus":"resolved","umaResolutionStatuses":"[]","umaReward":"5","updatedAt":"2024-12-02T02:35:28.059511Z","volume":"16270.347614","volume1mo":0,"volume1moAmm":0,"volume1moClob":0,"volume1wk":0,"volume1wkAmm":0,"volume1wkClob":0,"volume1yr":0,"volume1yrAmm":0,"volume1yrClob":0,"volumeClob":16270.347614,"volumeNum":16270.347614},{"acceptingOrders":false,"acceptingOrdersTimestamp":"2024-10-23T17:53:55Z","active":true,"approved":true,"archived":false,"automaticallyActive":true,"automaticallyResolved":true,"bestAsk":0.001,"clearBookOnStart":true,"clobRewards":[{"assetAddress":"0x2791Bca1f2de4661ED88A30C99A7a9449Aa84174","conditionId":"0x079a9f7ace19cdca701739d0c726a4ca3e5f3e098b45fb8dec6d98224c18b0ef","endDate":"2500-12-31","id":"9187","rewardsAmount":0,"rewardsDailyRate":5,"startDate":"2024-10-23"}],"clobTokenIds":"[\"77369813972373281494056878413808305294166200310819313501789756609916487521806\", \"90343978455430205602576405477191731041068488738581405938277825775798069801710\"]","closed":true,"closedTime":"2024-11-24 04:09:15+00","conditionId":"0x079a9f7ace19cdca701739d0c726a4ca3e5f3e098b45fb8dec6d98224c18b0ef","createdAt":"2024-10-23T00:15:47.4472Z","cyom":false,"deploying":false,"description":"This market will resolve to “Yes” if New York City win the 2024 MLS Cup. Otherwise, this market will resolve to “No”.\n\nIf at any point it becomes impossible for this team to win the MLS Cup based on the rules of the MLS (e.g., they are eliminated in the playoff bracket), this market will resolve immediately to “No”.\n\nThe resolution source for this market will be information from the MLS.","enableOrderBook":true,"endDate":"2024-12-07T12:00:00Z","endDateIso":"2024-12-07","featured":false,"feesEnabled":false,"funded":false,"groupItemThreshold":"9","groupItemTitle":"New York City FC","hasReviewedDates":true,"holdingRewardsEnabled":false,"icon":"https://polymarket-upload.s3.us-east-2.amazonaws.com/will-new-york-city-fc-win-the-mls-cup-amwUr42ceJQh.png","id":"510690","image":"https://polymarket-upload.s3.us-east-2.amazonaws.com/will-new-york-city-fc-win-the-mls-cup-amwUr42ceJQh.png","lastTradePrice":1,"manualActivation":false,"marketMakerAddress":"","negRisk":true,"negRiskMarketID":"0xd0558ff338582fd13f5a87a76983b6991e09f54106bd471a555bdc77151c9c00","negRiskOther":false,"negRiskRequestID":"0xf6faeffb657fa66e53ad9e4287424cece402f9525ea1d10daa09788271480bf1","new":false,"oneDayPriceChange":-0.1,"oneHourPriceChange":0,"oneMonthPriceChange":0,"oneWeekPriceChange":0,"oneYearPriceChange":0,"orderMinSize":5,"orderPriceMinTickSize":0.001,"outcomePrices":"[\"0\", \"1\"]","outcomes":"[\"Yes\", \"No\"]","pagerDutyNotificationEnabled":false,"pendingDeployment":false,"question":"Will New York City FC win the MLS Cup?","questionID":"0xd0558ff338582fd13f5a87a76983b6991e09f54106bd471a555bdc77151c9c09","ready":false,"requiresTranslation":false,"resolutionSource":"","resolvedBy":"0x2F5e3684cb1F318ec51b00Edba38d79Ac2c0aA9d","restricted":true,"rewardsMaxSpread":3.5,"rewardsMinSize":50,"rfqEnabled":false,"seriesColor":"","showGmpOutcome":false,"showGmpSeries":false,"slug":"will-new-york-city-fc-win-the-mls-cup","spread":0.001,"startDate":"2024-10-23T17:55:05.939417Z","startDateIso":"2024-10-23","submitted_by":"0x91430CaD2d3975766499717fA0D66A78D814E5c5","umaBond":"500","umaEndDate":"2024-11-24T04:09:15Z","umaResolutionStatus":"resolved","umaResolutionStatuses":"[]","umaReward":"5","updatedAt":"2024-11-25T01:19:46.33265Z","volume":"2479.736285","volume1mo":0,"volume1moAmm":0,"volume1moClob":0,"volume1wk":0,"volume1wkAmm":0,"volume1wkClob":0,"volume1yr":0,"volume1yrAmm":0,"volume1yrClob":0,"volumeClob":2479.736285,"volumeNum":2479.736285},{"acceptingOrders":false,"acceptingOrdersTimestamp":"2024-10-23T17:54:25Z","active":true,"approved":true,"archived":false,"automaticallyActive":true,"automaticallyResolved":true,"bestAsk":0.001,"clearBookOnStart":true,"clobRewards":[{"assetAddress":"0x2791Bca1f2de4661ED88A30C99A7a9449Aa84174","conditionId":"0xda740dd46fe066e40fc812b83e2e7a09760e8535e82636f30bda81b27ad24d22","endDate":"2500-12-31","id":"9186","rewardsAmount":0,"rewardsDailyRate":5,"startDate":"2024-10-23"}],"clobTokenIds":"[\"39925505282420626857548092591378102991122079197745584034625607381079370661153\", \"79989293596183513407676111310937901444324996289907500564341409944309352527071\"]","closed":true,"closedTime":"2024-11-10 17:32:12+00","conditionId":"0xda740dd46fe066e40fc812b83e2e7a09760e8535e82636f30bda81b27ad24d22","createdAt":"2024-10-23T15:24:06.849316Z","cyom":false,"deploying":false,"description":"This market will resolve to “Yes” if the Colorado Rapids win the 2024 MLS Cup. Otherwise, this market will resolve to “No.”\n\nIf at any point it becomes impossible for this team to win the MLS Cup based on the rules of the MLS (e.g., they are eliminated in the playoff bracket), this market will resolve immediately to “No.”\n\nThe resolution source for this market will be information from the MLS.","enableOrderBook":true,"endDate":"2024-10-07T12:00:00Z","endDateIso":"2024-10-07","featured":false,"feesEnabled":false,"funded":false,"groupItemThreshold":"10","groupItemTitle":"Colorado Rapids","hasReviewedDates":true,"holdingRewardsEnabled":false,"icon":"https://polymarket-upload.s3.us-east-2.amazonaws.com/will-the-colorado-rapids-win-the-2024-mls-cup-H-519acz_o54.png","id":"510694","image":"https://polymarket-upload.s3.us-east-2.amazonaws.com/will-the-colorado-rapids-win-the-2024-mls-cup-H-519acz_o54.png","lastTradePrice":1,"manualActivation":false,"marketMakerAddress":"","negRisk":true,"negRiskMarketID":"0xd0558ff338582fd13f5a87a76983b6991e09f54106bd471a555bdc77151c9c00","negRiskOther":false,"negRiskRequestID":"0x64d1d41e6ccb175a5173799a06f903058739fe511121bf5594f48d568479f81a","new":false,"oneDayPriceChange":-0.0015,"oneHourPriceChange":0,"oneMonthPriceChange":0,"oneWeekPriceChange":0,"oneYearPriceChange":0,"orderMinSize":5,"orderPriceMinTickSize":0.001,"outcomePrices":"[\"0\", \"1\"]","outcomes":"[\"Yes\", \"No\"]","pagerDutyNotificationEnabled":false,"pendingDeployment":false,"question":"Will the Colorado Rapids win the 2024 MLS Cup?","questionID":"0xd0558ff338582fd13f5a87a76983b6991e09f54106bd471a555bdc77151c9c0a","ready":false,"requiresTranslation":false,"resolutionSource":"","resolvedBy":"0x2F5e3684cb1F318ec51b00Edba38d79Ac2c0aA9d","restricted":true,"rewardsMaxSpread":3.5,"rewardsMinSize":50,"rfqEnabled":false,"seriesColor":"","showGmpOutcome":false,"showGmpSeries":false,"slug":"will-the-colorado-rapids-win-the-2024-mls-cup","spread":0.001,"startDate":"2024-10-23T17:55:38.355028Z","startDateIso":"2024-10-23","submitted_by":"0x91430CaD2d3975766499717fA0D66A78D814E5c5","umaBond":"500","umaEndDate":"2024-11-10T17:32:12Z","umaResolutionStatus":"resolved","umaResolutionStatuses":"[]","umaReward":"5","updatedAt":"2024-11-11T14:22:37.947657Z","volume":"50755.224","volume1mo":0,"volume1moAmm":0,"volume1moClob":0,"volume1wk":0,"volume1wkAmm":0,"volume1wkClob":0,"volume1yr":0,"volume1yrAmm":0,"volume1yrClob":0,"volumeClob":50755.224,"volumeNum":50755.224},{"acceptingOrders":false,"acceptingOrdersTimestamp":"2024-10-23T17:54:47Z","active":true,"approved":true,"archived":false,"automaticallyActive":true,"automaticallyResolved":true,"bestAsk":0.005,"clearBookOnStart":true,"clobRewards":[{"assetAddress":"0x2791Bca1f2de4661ED88A30C99A7a9449Aa84174","conditionId":"0x379fadc3117013c7a1d674ccfd4d3cc519b44450df766a674cd78a10ae3a1990","endDate":"2500-12-31","id":"9185","rewardsAmount":0,"rewardsDailyRate":5,"startDate":"2024-10-23"}],"clobTokenIds":"[\"41469928964642842045395301661095290768303868030994832287232634878797524914375\", \"103856878605725206143241654903920969362868609409940009006690259466840864712294\"]","closed":true,"closedTime":"2024-11-10 19:48:39+00","conditionId":"0x379fadc3117013c7a1d674ccfd4d3cc519b44450df766a674cd78a10ae3a1990","createdAt":"2024-10-23T15:25:43.361031Z","cyom":false,"deploying":false,"description":"This market will resolve to “Yes” if Charlotte FC win the 2024 MLS Cup. Otherwise, this market will resolve to “No.”\n\nIf at any point it becomes impossible for this team to win the MLS Cup based on the rules of the MLS (e.g., they are eliminated in the playoff bracket), this market will resolve immediately to “No.”\n\nThe resolution source for this market will be information from the MLS.","enableOrderBook":true,"endDate":"2024-12-08T12:00:00Z","endDateIso":"2024-12-08","featured":false,"feesEnabled":false,"funded":false,"groupItemThreshold":"11","groupItemTitle":"Charlotte FC","hasReviewedDates":true,"holdingRewardsEnabled":false,"icon":"https://polymarket-upload.s3.us-east-2.amazonaws.com/will-charlotte-fc-win-the-2024-mls-cup-0E5TwsSB0bIW.png","id":"510695","image":"https://polymarket-upload.s3.us-east-2.amazonaws.com/will-charlotte-fc-win-the-2024-mls-cup-0E5TwsSB0bIW.png","lastTradePrice":1,"manualActivation":false,"marketMakerAddress":"","negRisk":true,"negRiskMarketID":"0xd0558ff338582fd13f5a87a76983b6991e09f54106bd471a555bdc77151c9c00","negRiskOther":false,"negRiskRequestID":"0x0f82e1c5a803fc22960c675cc5396bbfdecb165c2d304b3b56b519366fedf348","new":false,"oneDayPriceChange":-0.011,"oneHourPriceChange":0,"oneMonthPriceChange":0,"oneWeekPriceChange":0,"oneYearPriceChange":0,"orderMinSize":5,"orderPriceMinTickSize":0.001,"outcomePrices":"[\"0\", \"1\"]","outcomes":"[\"Yes\", \"No\"]","pagerDutyNotificationEnabled":false,"pendingDeployment":false,"question":"Will Charlotte FC win the 2024 MLS Cup?","questionID":"0xd0558ff338582fd13f5a87a76983b6991e09f54106bd471a555bdc77151c9c0b","ready":false,"requiresTranslation":false,"resolutionSource":"","resolvedBy":"0x2F5e3684cb1F318ec51b00Edba38d79Ac2c0aA9d","restricted":true,"rewardsMaxSpread":3.5,"rewardsMinSize":50,"rfqEnabled":false,"seriesColor":"","showGmpOutcome":false,"showGmpSeries":false,"slug":"will-charlotte-fc-win-the-2024-mls-cup","spread":0.005,"startDate":"2024-10-23T17:55:53.541651Z","startDateIso":"2024-10-23","submitted_by":"0x91430CaD2d3975766499717fA0D66A78D814E5c5","umaBond":"500","umaEndDate":"2024-11-10T19:48:39Z","umaResolutionStatus":"resolved","umaResolutionStatuses":"[]","umaReward":"5","updatedAt":"2024-11-11T16:42:42.806322Z","volume":"10302.243533","volume1mo":0,"volume1moAmm":0,"volume1moClob":0,"volume1wk":0,"volume1wkAmm":0,"volume1wkClob":0,"volume1yr":0,"volume1yrAmm":0,"volume1yrClob":0,"volumeClob":10302.243533,"volumeNum":10302.243533},{"acceptingOrders":false,"acceptingOrdersTimestamp":"2024-10-23T17:55:37Z","active":true,"approved":true,"archived":false,"automaticallyActive":true,"automaticallyResolved":true,"bestAsk":0.001,"clearBookOnStart":true,"clobRewards":[{"assetAddress":"0x2791Bca1f2de4661ED88A30C99A7a9449Aa84174","conditionId":"0xb87756f380531b84d184da661c216a5452d1e5a210d52bcb6470e8d787c1901d","endDate":"2500-12-31","id":"9184","rewardsAmount":0,"rewardsDailyRate":30,"startDate":"2024-10-23"}],"clobTokenIds":"[\"98790224792098906531889995040793870986111833651174671939508465330650453861099\", \"10790031822696490246632981022913844186532582664806327810947206256328268428714\"]","closed":true,"closedTime":"2024-12-08 02:34:09+00","conditionId":"0xb87756f380531b84d184da661c216a5452d1e5a210d52bcb6470e8d787c1901d","createdAt":"2024-10-23T15:26:15.147577Z","cyom":false,"deploying":false,"description":"This market will resolve to “Yes” if the New York Red Bulls win the 2024 MLS Cup. Otherwise, this market will resolve to “No.”\n\nIf at any point it becomes impossible for this team to win the MLS Cup based on the rules of the MLS (e.g., they are eliminated in the playoff bracket), this market will resolve immediately to “No.”\n\nThe resolution source for this market will be information from the MLS.","enableOrderBook":true,"endDate":"2024-12-07T12:00:00Z","endDateIso":"2024-12-07","featured":false,"feesEnabled":false,"funded":false,"groupItemThreshold":"12","groupItemTitle":"New York Red Bulls","hasReviewedDates":true,"holdingRewardsEnabled":false,"icon":"https://polymarket-upload.s3.us-east-2.amazonaws.com/will-the-new-york-red-bulls-win-the-2024-mls-cup-nq-cqOzAgnAb.png","id":"510696","image":"https://polymarket-upload.s3.us-east-2.amazonaws.com/will-the-new-york-red-bulls-win-the-2024-mls-cup-nq-cqOzAgnAb.png","lastTradePrice":1,"manualActivation":false,"marketMakerAddress":"","negRisk":true,"negRiskMarketID":"0xd0558ff338582fd13f5a87a76983b6991e09f54106bd471a555bdc77151c9c00","negRiskOther":false,"negRiskRequestID":"0x7f38d02d360c161d9346feb611a155217fccf72921613c8874d1e75f819c0be7","new":false,"oneDayPriceChange":-0.3345,"oneHourPriceChange":0,"oneMonthPriceChange":0,"oneWeekPriceChange":0,"oneYearPriceChange":0,"orderMinSize":5,"orderPriceMinTickSize":0.001,"outcomePrices":"[\"0\", \"1\"]","outcomes":"[\"Yes\", \"No\"]","pagerDutyNotificationEnabled":false,"pendingDeployment":false,"question":"Will the New York Red Bulls win the 2024 MLS Cup?","questionID":"0xd0558ff338582fd13f5a87a76983b6991e09f54106bd471a555bdc77151c9c0c","ready":false,"requiresTranslation":false,"resolutionSource":"","resolvedBy":"0x2F5e3684cb1F318ec51b00Edba38d79Ac2c0aA9d","restricted":true,"rewardsMaxSpread":3.5,"rewardsMinSize":50,"rfqEnabled":false,"seriesColor":"","showGmpOutcome":false,"showGmpSeries":false,"slug":"will-the-new-york-red-bulls-win-the-2024-mls-cup","spread":0.001,"startDate":"2024-10-23T17:56:46.06847Z","startDateIso":"2024-10-23","submitted_by":"0x91430CaD2d3975766499717fA0D66A78D814E5c5","umaBond":"500","umaEndDate":"2024-12-08T02:34:09Z","umaResolutionStatus":"resolved","umaResolutionStatuses":"[]","umaReward":"5","updatedAt":"2024-12-08T23:39:29.737334Z","volume":"9627.630664","volume1mo":0,"volume1moAmm":0,"volume1moClob":0,"volume1wk":0,"volume1wkAmm":0,"volume1wkClob":0,"volume1yr":0,"volume1yrAmm":0,"volume1yrClob":0,"volumeClob":9627.630664,"volumeNum":9627.630664},{"acceptingOrders":false,"acceptingOrdersTimestamp":"2024-10-23T17:56:29Z","active":true,"approved":true,"archived":false,"automaticallyActive":true,"automaticallyResolved":true,"bestAsk":0.001,"clearBookOnStart":true,"clobRewards":[{"assetAddress":"0x2791Bca1f2de4661ED88A30C99A7a9449Aa84174","conditionId":"0xf20cf747730a2a3539a652abb6a6c6b54e2eaf4cb6a6120a685af567014db789","endDate":"2500-12-31","id":"9183","rewardsAmount":0,"rewardsDailyRate":5,"startDate":"2024-10-23"}],"clobTokenIds":"[\"21246585287438775496034164929022871781096668791266236039187382371021182178339\", \"109880626493079968360187733933149432037945124192858527074155365093068693656276\"]","closed":true,"closedTime":"2024-11-25 04:36:24+00","conditionId":"0xf20cf747730a2a3539a652abb6a6c6b54e2eaf4cb6a6120a685af567014db789","createdAt":"2024-10-23T15:35:29.941534Z","cyom":false,"deploying":false,"description":"This market will resolve to “Yes” if Minnesota United win the 2024 MLS Cup. Otherwise, this market will resolve to “No.”\n\nIf at any point it becomes impossible for this team to win the MLS Cup based on the rules of the MLS (e.g., they are eliminated in the playoff bracket), this market will resolve immediately to “No.”\n\nThe resolution source for this market will be information from the MLS.","enableOrderBook":true,"endDate":"2024-12-07T12:00:00Z","endDateIso":"2024-12-07","featured":false,"feesEnabled":false,"funded":false,"groupItemThreshold":"13","groupItemTitle":"Minnesota United","hasReviewedDates":true,"holdingRewardsEnabled":false,"icon":"https://polymarket-upload.s3.us-east-2.amazonaws.com/will-minnesota-united-win-the-2024-mls-cup-RNBN0QBB-ycp.png","id":"510700","image":"https://polymarket-upload.s3.us-east-2.amazonaws.com/will-minnesota-united-win-the-2024-mls-cup-RNBN0QBB-ycp.png","lastTradePrice":1,"manualActivation":false,"marketMakerAddress":"","negRisk":true,"negRiskMarketID":"0xd0558ff338582fd13f5a87a76983b6991e09f54106bd471a555bdc77151c9c00","negRiskOther":false,"negRiskRequestID":"0x77683739de12e914b0dbc5a49132bd156f312aa5d525e45dd3746495860701c1","new":false,"oneDayPriceChange":-0.056,"oneHourPriceChange":0,"oneMonthPriceChange":0,"oneWeekPriceChange":0,"oneYearPriceChange":0,"orderMinSize":5,"orderPriceMinTickSize":0.001,"outcomePrices":"[\"0\", \"1\"]","outcomes":"[\"Yes\", \"No\"]","pagerDutyNotificationEnabled":false,"pendingDeployment":false,"question":"Will Minnesota United win the 2024 MLS Cup?","questionID":"0xd0558ff338582fd13f5a87a76983b6991e09f54106bd471a555bdc77151c9c0d","ready":false,"requiresTranslation":false,"resolutionSource":"","resolvedBy":"0x2F5e3684cb1F318ec51b00Edba38d79Ac2c0aA9d","restricted":true,"rewardsMaxSpread":3.5,"rewardsMinSize":50,"rfqEnabled":false,"seriesColor":"","showGmpOutcome":false,"showGmpSeries":false,"slug":"will-minnesota-united-win-the-2024-mls-cup","spread":0.001,"startDate":"2024-10-23T17:57:38.958015Z","startDateIso":"2024-10-23","submitted_by":"0x91430CaD2d3975766499717fA0D66A78D814E5c5","umaBond":"500","umaEndDate":"2024-11-25T04:36:24Z","umaResolutionStatus":"resolved","umaResolutionStatuses":"[]","umaReward":"5","updatedAt":"2024-11-26T01:39:43.901914Z","volume":"12217.798291","volume1mo":0,"volume1moAmm":0,"volume1moClob":0,"volume1wk":0,"volume1wkAmm":0,"volume1wkClob":0,"volume1yr":0,"volume1yrAmm":0,"volume1yrClob":0,"volumeClob":12217.798291,"volumeNum":12217.798291},{"acceptingOrders":false,"acceptingOrdersTimestamp":"2024-10-23T17:56:53Z","active":true,"approved":true,"archived":false,"automaticallyActive":true,"automaticallyResolved":true,"bestAsk":0.001,"clearBookOnStart":true,"clobRewards":[{"assetAddress":"0x2791Bca1f2de4661ED88A30C99A7a9449Aa84174","conditionId":"0x1677c9767312d900ea10e4615d29e96f00b9849938b9487ad5ad6d5fc048ad22","endDate":"2500-12-31","id":"9182","rewardsAmount":0,"rewardsDailyRate":5,"startDate":"2024-10-23"}],"clobTokenIds":"[\"42611520647740449198304146437187796586753026374229309119527804198957999768499\", \"92096720446759766795801649014521919584896501470016519743805315470911104563150\"]","closed":true,"closedTime":"2024-11-10 20:38:24+00","conditionId":"0x1677c9767312d900ea10e4615d29e96f00b9849938b9487ad5ad6d5fc048ad22","createdAt":"2024-10-23T15:35:52.107635Z","cyom":false,"deploying":false,"description":"This market will resolve to “Yes” if the Portland Timbers win the 2024 MLS Cup. Otherwise, this market will resolve to “No.”\n\nIf at any point it becomes impossible for this team to win the MLS Cup based on the rules of the MLS (e.g., they are eliminated in the playoff bracket), this market will resolve immediately to “No.”\n\nThe resolution source for this market will be information from the MLS.","enableOrderBook":true,"endDate":"2024-12-07T12:00:00Z","endDateIso":"2024-12-07","featured":false,"feesEnabled":false,"funded":false,"groupItemThreshold":"14","groupItemTitle":"Portland Timbers","hasReviewedDates":true,"holdingRewardsEnabled":false,"icon":"https://polymarket-upload.s3.us-east-2.amazonaws.com/will-the-portland-timbers-win-the-2024-mls-cup-L-0kbbqDR0hQ.png","id":"510701","image":"https://polymarket-upload.s3.us-east-2.amazonaws.com/will-the-portland-timbers-win-the-2024-mls-cup-L-0kbbqDR0hQ.png","lastTradePrice":1,"manualActivation":false,"marketMakerAddress":"","negRisk":true,"negRiskMarketID":"0xd0558ff338582fd13f5a87a76983b6991e09f54106bd471a555bdc77151c9c00","negRiskOther":false,"negRiskRequestID":"0xc5378d0674682496e6c0beb287b0f86503aac17e684c7b8a9220dab53062169f","new":false,"oneDayPriceChange":-0.003,"oneHourPriceChange":0,"oneMonthPriceChange":0,"oneWeekPriceChange":0,"oneYearPriceChange":0,"orderMinSize":5,"orderPriceMinTickSize":0.001,"outcomePrices":"[\"0\", \"1\"]","outcomes":"[\"Yes\", \"No\"]","pagerDutyNotificationEnabled":false,"pendingDeployment":false,"question":"Will the Portland Timbers win the 2024 MLS Cup?","questionID":"0xd0558ff338582fd13f5a87a76983b6991e09f54106bd471a555bdc77151c9c0e","ready":false,"requiresTranslation":false,"resolutionSource":"","resolvedBy":"0x2F5e3684cb1F318ec51b00Edba38d79Ac2c0aA9d","restricted":true,"rewardsMaxSpread":3.5,"rewardsMinSize":50,"rfqEnabled":false,"seriesColor":"","showGmpOutcome":false,"showGmpSeries":false,"slug":"will-the-portland-timbers-win-the-2024-mls-cup","spread":0.001,"startDate":"2024-10-23T17:58:05.423276Z","startDateIso":"2024-10-23","submitted_by":"0x91430CaD2d3975766499717fA0D66A78D814E5c5","umaBond":"500","umaEndDate":"2024-11-10T20:38:24Z","umaResolutionStatus":"resolved","umaResolutionStatuses":"[]","umaReward":"5","updatedAt":"2024-11-11T18:53:12.750278Z","volume":"274420.461832","volume1mo":0,"volume1moAmm":0,"volume1moClob":0,"volume1wk":0,"volume1wkAmm":0,"volume1wkClob":0,"volume1yr":0,"volume1yrAmm":0,"volume1yrClob":0,"volumeClob":274420.461832,"volumeNum":274420.461832},{"acceptingOrders":false,"acceptingOrdersTimestamp":"2024-10-23T17:58:25Z","active":true,"approved":true,"archived":false,"automaticallyActive":true,"automaticallyResolved":true,"bestAsk":0.001,"clearBookOnStart":true,"clobRewards":[{"assetAddress":"0x2791Bca1f2de4661ED88A30C99A7a9449Aa84174","conditionId":"0x6ed233b79c2e135ae88d3171770e53759e188f5a506a4a353d8f6eaef31d1ccb","endDate":"2500-12-31","id":"9181","rewardsAmount":0,"rewardsDailyRate":5,"startDate":"2024-10-23"}],"clobTokenIds":"[\"79345849628578541874489102578869906048420713576918889847020807586432527071282\", \"25756617593424070667453323376700881194064367386656407749514153756068323121689\"]","closed":true,"closedTime":"2024-11-10 20:47:35+00","conditionId":"0x6ed233b79c2e135ae88d3171770e53759e188f5a506a4a353d8f6eaef31d1ccb","createdAt":"2024-10-23T15:36:15.387752Z","cyom":false,"deploying":false,"description":"This market will resolve to “Yes” if the Vancouver Whitecaps win the 2024 MLS Cup. Otherwise, this market will resolve to “No.”\n\nIf at any point it becomes impossible for this team to win the MLS Cup based on the rules of the MLS (e.g., they are eliminated in the playoff bracket), this market will resolve immediately to “No.”\n\nThe resolution source for this market will be information from the MLS.","enableOrderBook":true,"endDate":"2024-12-07T12:00:00Z","endDateIso":"2024-12-07","featured":false,"feesEnabled":false,"funded":false,"groupItemThreshold":"15","groupItemTitle":"Vancouver Whitecaps","hasReviewedDates":true,"holdingRewardsEnabled":false,"icon":"https://polymarket-upload.s3.us-east-2.amazonaws.com/will-the-vancouver-whitecaps-win-the-2024-mls-cup-y7txUc61NGb6.png","id":"510702","image":"https://polymarket-upload.s3.us-east-2.amazonaws.com/will-the-vancouver-whitecaps-win-the-2024-mls-cup-y7txUc61NGb6.png","lastTradePrice":1,"manualActivation":false,"marketMakerAddress":"","negRisk":true,"negRiskMarketID":"0xd0558ff338582fd13f5a87a76983b6991e09f54106bd471a555bdc77151c9c00","negRiskOther":false,"negRiskRequestID":"0x408342d568ef1d7331b572eae12d748e9652203a7025d98f842c1f3d1e769e31","new":false,"oneDayPriceChange":-0.0045,"oneHourPriceChange":0,"oneMonthPriceChange":0,"oneWeekPriceChange":0,"oneYearPriceChange":0,"orderMinSize":5,"orderPriceMinTickSize":0.001,"outcomePrices":"[\"0\", \"1\"]","outcomes":"[\"Yes\", \"No\"]","pagerDutyNotificationEnabled":false,"pendingDeployment":false,"question":"Will the Vancouver Whitecaps win the 2024 MLS Cup?","questionID":"0xd0558ff338582fd13f5a87a76983b6991e09f54106bd471a555bdc77151c9c0f","ready":false,"requiresTranslation":false,"resolutionSource":"","resolvedBy":"0x2F5e3684cb1F318ec51b00Edba38d79Ac2c0aA9d","restricted":true,"rewardsMaxSpread":3.5,"rewardsMinSize":50,"rfqEnabled":false,"seriesColor":"","showGmpOutcome":false,"showGmpSeries":false,"slug":"will-the-vancouver-whitecaps-win-the-2024-mls-cup","spread":0.001,"startDate":"2024-10-23T17:59:35.974844Z","startDateIso":"2024-10-23","submitted_by":"0x91430CaD2d3975766499717fA0D66A78D814E5c5","umaBond":"500","umaEndDate":"2024-11-10T20:47:35Z","umaResolutionStatus":"resolved","umaResolutionStatuses":"[]","umaReward":"5","updatedAt":"2024-11-11T17:02:40.769862Z","volume":"22045.354227","volume1mo":0,"volume1moAmm":0,"volume1moClob":0,"volume1wk":0,"volume1wkAmm":0,"volume1wkClob":0,"volume1yr":0,"volume1yrAmm":0,"volume1yrClob":0,"volumeClob":22045.354227,"volumeNum":22045.354227},{"acceptingOrders":false,"acceptingOrdersTimestamp":"2024-10-23T17:58:47Z","active":true,"approved":true,"archived":false,"automaticallyActive":true,"automaticallyResolved":true,"bestAsk":0.001,"clearBookOnStart":true,"clobRewards":[{"assetAddress":"0x2791Bca1f2de4661ED88A30C99A7a9449Aa84174","conditionId":"0xba7e3d98ea16307c793a2a42101aeb1ad39b17cdabdfe836e435427e2ad596bd","endDate":"2500-12-31","id":"9180","rewardsAmount":0,"rewardsDailyRate":5,"startDate":"2024-10-23"}],"clobTokenIds":"[\"17804184522017959761536519166233146770070780812958801754014786943578911730809\", \"71623175676585238510677665656043072674760585477373643493405925051104169361150\"]","closed":true,"closedTime":"2024-11-25 01:50:02+00","conditionId":"0xba7e3d98ea16307c793a2a42101aeb1ad39b17cdabdfe836e435427e2ad596bd","createdAt":"2024-10-23T15:46:01.452094Z","cyom":false,"deploying":false,"description":"This market will resolve to “Yes” if Atlanta United win the 2024 MLS Cup. Otherwise, this market will resolve to “No.”\n\nIf at any point it becomes impossible for this team to win the MLS Cup based on the rules of the MLS (e.g., they are eliminated in the playoff bracket), this market will resolve immediately to “No.”\n\nThe resolution source for this market will be information from the MLS.","enableOrderBook":true,"endDate":"2024-12-07T12:00:00Z","endDateIso":"2024-12-07","featured":false,"feesEnabled":false,"funded":false,"groupItemThreshold":"16","groupItemTitle":"Atlanta United","hasReviewedDates":true,"holdingRewardsEnabled":false,"icon":"https://polymarket-upload.s3.us-east-2.amazonaws.com/will-atlanta-united-win-the-2024-mls-cup-pjYx_22pzuW9.png","id":"510705","image":"https://polymarket-upload.s3.us-east-2.amazonaws.com/will-atlanta-united-win-the-2024-mls-cup-pjYx_22pzuW9.png","lastTradePrice":1,"manualActivation":false,"marketMakerAddress":"","negRisk":true,"negRiskMarketID":"0xd0558ff338582fd13f5a87a76983b6991e09f54106bd471a555bdc77151c9c00","negRiskOther":false,"negRiskRequestID":"0xa5e01a3b444f22eee4cdc5c0bc8848897b7de427c5f7c3d0ba7bf2a525b3c2b0","new":false,"oneDayPriceChange":-0.1235,"oneHourPriceChange":0,"oneMonthPriceChange":0,"oneWeekPriceChange":0,"oneYearPriceChange":0,"orderMinSize":5,"orderPriceMinTickSize":0.001,"outcomePrices":"[\"0\", \"1\"]","outcomes":"[\"Yes\", \"No\"]","pagerDutyNotificationEnabled":false,"pendingDeployment":false,"question":"Will Atlanta United win the 2024 MLS Cup?","questionID":"0xd0558ff338582fd13f5a87a76983b6991e09f54106bd471a555bdc77151c9c10","ready":false,"requiresTranslation":false,"resolutionSource":"","resolvedBy":"0x2F5e3684cb1F318ec51b00Edba38d79Ac2c0aA9d","restricted":true,"rewardsMaxSpread":3.5,"rewardsMinSize":50,"rfqEnabled":false,"seriesColor":"","showGmpOutcome":false,"showGmpSeries":false,"slug":"will-atlanta-united-win-the-2024-mls-cup","spread":0.001,"startDate":"2024-10-23T17:59:56.208551Z","startDateIso":"2024-10-23","submitted_by":"0x91430CaD2d3975766499717fA0D66A78D814E5c5","umaBond":"500","umaEndDate":"2024-11-25T01:50:02Z","umaResolutionStatus":"resolved","umaResolutionStatuses":"[]","umaReward":"5","updatedAt":"2024-11-25T22:39:53.341093Z","volume":"14871.663873","volume1mo":0,"volume1moAmm":0,"volume1moClob":0,"volume1wk":0,"volume1wkAmm":0,"volume1wkClob":0,"volume1yr":0,"volume1yrAmm":0,"volume1yrClob":0,"volumeClob":14871.663873,"volumeNum":14871.663873}],"negRisk":true,"negRiskAugmented":false,"negRiskMarketID":"0xd0558ff338582fd13f5a87a76983b6991e09f54106bd471a555bdc77151c9c00","new":false,"openInterest":0,"pendingDeployment":false,"requiresTranslation":false,"resolutionSource":"","restricted":true,"showAllOutcomes":true,"showMarketImages":true,"slug":"mls-cup-winner","sortBy":"price","startDate":"2024-10-23T18:01:29.975696Z","tags":[{"createdAt":"2023-10-24T22:37:50.31Z","forceHide":true,"forceShow":false,"id":"1","label":"Sports","publishedAt":"2023-10-24 22:37:50.296+00","requiresTranslation":false,"slug":"sports","updatedAt":"2025-12-18T02:44:02.245397Z","updatedBy":15},{"id":"100100","label":"MLS","requiresTranslation":false,"slug":"mls","updatedAt":"2025-12-18T02:46:37.347877Z"},{"createdAt":"2023-11-02T22:13:47.21Z","id":"397","label":"futures","publishedAt":"2023-11-02 22:13:47.199+00","requiresTranslation":false,"slug":"futures","updatedAt":"2025-12-18T02:17:52.794817Z"},{"createdAt":"2024-08-21T16:31:18.953213Z","forceShow":false,"id":"100350","label":"Soccer","requiresTranslation":false,"slug":"soccer","updatedAt":"2025-12-18T02:52:11.138841Z"}],"ticker":"mls-cup-winner","title":"MLS Cup Winner","updatedAt":"2024-12-09T00:51:39.050139Z","volume":1460858.20816,"volume1mo":0,"volume1wk":0,"volume1yr":0}