{
  "entity": "market",
  "market_id": "514890",
  "folder_rule": "market.createdAt (fallback: market.published_at)",
  "folder_dt_utc": "2024-12-05T21:40:27.059827Z",
  "market_createdAt": "2024-12-05T21:40:27.059827Z",
  "market_updatedAt": "2024-12-17T17:39:22.201889Z",
  "market_startDate": "2024-12-10T21:03:59.43634Z",
  "market_endDate": "2024-12-31T12:00:00Z",
  "market_closedTime": "2024-12-16 20:34:30+00",
  "conditionId": "0xe5f313dad2140cb3816990f148de42ccaea709a6c1b31b8f157a32c383aa8a5d",
  "slug": "will-coinbase-announce-just-a-chill-guy-as-next-listing",
  "question": "Will Coinbase announce Just a chill guy as next listing?"
}