{"acceptingOrders":false,"acceptingOrdersTimestamp":"2024-12-01T05:17:58Z","active":true,"approved":true,"archived":false,"automaticallyActive":true,"automaticallyResolved":true,"bestAsk":0.001,"clearBookOnStart":true,"clobTokenIds":"[\"69520195084813038456918817138304783090285747088044543053152726373704290454348\", \"73756858771859082714202944925503152037748489007706514610090236755404062941001\"]","closed":true,"closedTime":"2024-12-08 04:46:10+00","conditionId":"0x3a7291187dd61c9004a86c4dd70d099039dbb21491f8828e8b91df85541d20f1","createdAt":"2024-12-01T05:15:45.157054Z","cyom":false,"deploying":false,"description":"In the upcoming NBA game, scheduled for December 7 at 7:00PM ET:\nIf the Denver Nuggets win, the market will resolve to “Nuggets”.\nIf the Washington Wizards win, the market will resolve to “Wizards”.\nIf the game is not completed by December 14, 2024 (11:59 PM ET) or it ends in a tie, the market will resolve 50-50.","enableOrderBook":true,"endDate":"2024-12-15T00:00:00Z","endDateIso":"2024-12-15","events":[{"active":true,"archived":false,"automaticallyActive":true,"automaticallyResolved":true,"closed":true,"closedTime":"2024-12-08T04:46:10Z","commentCount":8125,"createdAt":"2024-12-01T05:15:45.145079Z","creationDate":"2024-12-08T00:00:00Z","cumulativeMarkets":false,"cyom":false,"deploying":false,"description":"In the upcoming NBA game, scheduled for December 7 at 7:00PM ET:\nIf the Denver Nuggets win, the market will resolve to “Nuggets”.\nIf the Washington Wizards win, the market will resolve to “Wizards”.\nIf the game is not completed by December 14, 2024 (11:59 PM ET) or it ends in a tie, the market will resolve 50-50.","elapsed":"","enableNegRisk":false,"enableOrderBook":true,"endDate":"2024-12-08T00:00:00Z","ended":true,"eventDate":"2024-12-07","eventWeek":7,"featured":false,"finishedTimestamp":"2024-12-08T02:33:08.292027Z","icon":"https://polymarket-upload.s3.us-east-2.amazonaws.com/nba.png","id":"14958","image":"https://polymarket-upload.s3.us-east-2.amazonaws.com/nba.png","live":false,"negRisk":false,"negRiskAugmented":false,"new":false,"openInterest":0,"pendingDeployment":false,"period":"FT","requiresTranslation":false,"restricted":true,"score":"113-122","series":[{"active":true,"archived":false,"closed":false,"commentCount":6279,"commentsEnabled":false,"competitive":"0","createdAt":"2022-10-13T00:36:01.131Z","createdBy":"15","featured":false,"icon":"https://polymarket-upload.s3.us-east-2.amazonaws.com/super+cool+basketball+in+red+and+blue+wow.png","id":"2","image":"https://polymarket-upload.s3.us-east-2.amazonaws.com/super+cool+basketball+in+red+and+blue+wow.png","layout":"default","new":false,"publishedAt":"2023-01-30 17:13:39.006+00","recurrence":"daily","requiresTranslation":false,"restricted":true,"seriesType":"single","slug":"nba","startDate":"2021-01-01T17:00:00Z","ticker":"nba","title":"NBA","updatedAt":"2026-01-06T13:36:33.878702Z","updatedBy":"15","volume24hr":0}],"seriesSlug":"nba","showAllOutcomes":false,"showMarketImages":true,"slug":"nba-den-was-2024-12-07","startDate":"2024-12-01T05:19:37.671515Z","startTime":"2024-12-08T00:00:00Z","ticker":"nba-den-was-2024-12-07","title":"Nuggets vs. Wizards","updatedAt":"2024-12-09T04:35:34.060316Z","volume":360918.30536,"volume1mo":0,"volume1wk":0,"volume1yr":0}],"fee":"20000000000000000","feesEnabled":false,"fpmmLive":true,"funded":false,"gameStartTime":"2024-12-08 00:00:00+00","groupItemTitle":"Nuggets vs. Wizards","hasReviewedDates":true,"holdingRewardsEnabled":false,"icon":"https://polymarket-upload.s3.us-east-2.amazonaws.com/nba.png","id":"514315","image":"https://polymarket-upload.s3.us-east-2.amazonaws.com/nba.png","lastTradePrice":1,"manualActivation":false,"marketMakerAddress":"0x74b22F5f6d003D93e8066D6da28A9a1b02be40b5","negRisk":false,"negRiskOther":false,"new":true,"notificationsEnabled":false,"oneDayPriceChange":-0.8845,"oneHourPriceChange":0,"oneMonthPriceChange":0,"oneWeekPriceChange":0,"oneYearPriceChange":0,"orderMinSize":5,"orderPriceMinTickSize":0.001,"outcomePrices":"[\"0\", \"1\"]","outcomes":"[\"Nuggets\", \"Wizards\"]","pagerDutyNotificationEnabled":false,"pendingDeployment":false,"question":"Nuggets vs. Wizards","questionID":"0x3d31c8205da6593addfcf71d38a801f00da2cc6e6267704c816f7f825b2dfd26","ready":false,"readyForCron":false,"requiresTranslation":false,"resolutionSource":"https://www.nba.com/","resolvedBy":"0x6A9D222616C90FcA5754cd1333cFD9b7fb6a4F74","restricted":true,"rewardsMaxSpread":0,"rewardsMinSize":0,"rfqEnabled":false,"secondsDelay":3,"sentDiscord":true,"slug":"nba-den-was-2024-12-07","spread":0.001,"startDate":"2024-12-01T05:19:21.796181Z","startDateIso":"2024-12-01","umaEndDate":"2024-12-08T04:46:10Z","umaResolutionStatus":"resolved","umaResolutionStatuses":"[]","updatedAt":"2024-12-09T04:35:30.999097Z","volume":"360918.30536","volume1mo":0,"volume1moAmm":0,"volume1moClob":0,"volume1wk":0,"volume1wkAmm":0,"volume1wkClob":0,"volume1yr":0,"volume1yrAmm":0,"volume1yrClob":0,"volumeClob":360918.30536,"volumeNum":360918.30536,"wideFormat":true}