{
  "entity": "market",
  "market_id": "254617",
  "folder_rule": "market.createdAt (fallback: market.published_at)",
  "folder_dt_utc": "2024-02-21T21:47:03.997000Z",
  "market_createdAt": "2024-02-21T21:47:03.997Z",
  "market_updatedAt": "2024-11-09T13:47:02.014503Z",
  "market_startDate": "2024-02-21T23:18:00Z",
  "market_endDate": "2024-12-30T00:00:00Z",
  "market_closedTime": "2024-11-08 16:35:21+00",
  "conditionId": "0x4ddba39e67b2f7f4a78808a4975fbdd8b591f73207b8f1fd9b607821481aa994",
  "slug": "sony-doesnt-release-playstation-5-pro-in-2024",
  "question": "Sony doesn't release Playstation 5 Pro in 2024?"
}