{
  "entity": "event",
  "event_id": "14417",
  "folder_rule": "event.createdAt (fallback: max(markets[].published_at))",
  "folder_dt_utc": "2024-11-14T19:02:32.405843Z",
  "event_createdAt": "2024-11-14T19:02:32.405843Z",
  "event_creationDate": "2024-11-14T20:41:03.228031Z",
  "event_startDate": "2024-11-14T20:41:03.228033Z",
  "event_endDate": "2024-11-15T12:00:00Z",
  "event_updatedAt": "2024-11-16T22:57:06.841699Z",
  "markets_len": 1,
  "market_ids": [
    "513031"
  ],
  "series_len": 0,
  "series_ids": [],
  "series_slug": null
}