{
  "entity": "market",
  "market_id": "513540",
  "folder_rule": "market.createdAt (fallback: market.published_at)",
  "folder_dt_utc": "2024-11-20T17:23:50.101751Z",
  "market_createdAt": "2024-11-20T17:23:50.101751Z",
  "market_updatedAt": "2024-12-04T15:11:11.469036Z",
  "market_startDate": "2024-11-20T18:59:31.44Z",
  "market_endDate": "2024-11-30T12:00:00Z",
  "market_closedTime": "2024-12-04 02:20:08+00",
  "conditionId": "0xa237df405308afa19050e92bda1da072628ce58cde69efa39b1c1c049029013e",
  "slug": "will-the-liberal-reform-party-win-the-most-seats-in-the-icelandic-parliamentary-election",
  "question": "Will the Liberal Reform Party win the most seats in the Icelandic parliamentary election?"
}