{
  "entity": "market",
  "market_id": "500698",
  "folder_rule": "market.createdAt (fallback: market.published_at)",
  "folder_dt_utc": "2024-04-04T17:02:27.351356Z",
  "market_createdAt": "2024-04-04T17:02:27.351356Z",
  "market_updatedAt": "2024-11-07T18:03:03.950113Z",
  "market_startDate": "2024-04-12T19:35:32.928Z",
  "market_endDate": "2024-11-05T12:00:00Z",
  "market_closedTime": "2024-11-06 21:45:37+00",
  "conditionId": "0x521a7fb05fa539cddc4b5c573fb3888a143b1262c394cce452189e67b53d0726",
  "slug": "will-a-democrat-win-mississippi-us-senate-election",
  "question": "Will a Democrat win Mississippi US Senate Election?"
}