{"acceptingOrders":false,"acceptingOrdersTimestamp":"2024-10-30T15:06:20Z","active":true,"approved":true,"archived":false,"automaticallyActive":true,"automaticallyResolved":true,"bestAsk":0.008,"clearBookOnStart":true,"clobTokenIds":"[\"19449429304997934641720510261137098298150779042689055023030474135822068433122\", \"15429862779030600414464709468822926026186348091809375977697784839938800352529\"]","closed":true,"closedTime":"2024-11-11 01:56:44+00","conditionId":"0x8da84fddaa700e09545ddb9a4b4af8760701bf4e752fbda4c3b25e73ff5d4ced","createdAt":"2024-10-29T22:24:30.92822Z","cyom":false,"deploying":false,"description":"This market will resolve to “Yes” if Sergio Perez wins the 2024 Brazilian Grand Prix scheduled for November 3, 2024. Otherwise, this market will resolve to “No.”\n\nIf the 2024 Brazilian Grand Prix is canceled or rescheduled to a date after November 17, 2024, this market will resolve to “No.”\n\nThe resolution source will be the official Formula 1 website and credible sports news reporting.","enableOrderBook":true,"endDate":"2024-11-03T12:00:00Z","endDateIso":"2024-11-03","events":[{"active":true,"archived":false,"automaticallyActive":true,"automaticallyResolved":true,"closed":true,"closedTime":"2024-11-11T01:56:44Z","commentCount":39,"createdAt":"2024-10-29T22:21:28.986688Z","creationDate":"2024-10-30T15:09:11.900648Z","cumulativeMarkets":false,"cyom":false,"deploying":false,"description":"This is a market on predicting the winner of the Brazilian Grand Prix in Formula 1 racing.","enableNegRisk":true,"enableOrderBook":true,"endDate":"2024-11-03T12:00:00Z","featured":false,"gmpChartMode":"default","icon":"https://polymarket-upload.s3.us-east-2.amazonaws.com/brazlian-grand-prix-winner-kKu5YYPchxJT.png","id":"13901","image":"https://polymarket-upload.s3.us-east-2.amazonaws.com/brazlian-grand-prix-winner-kKu5YYPchxJT.png","negRisk":true,"negRiskAugmented":false,"negRiskMarketID":"0xbf55bf389f1d1c01bb07d249defdc713675daa59871da998d5b29a78ba445300","new":false,"openInterest":0,"pendingDeployment":false,"requiresTranslation":false,"resolutionSource":"","restricted":true,"showAllOutcomes":true,"showMarketImages":true,"slug":"brazlian-grand-prix-winner","startDate":"2024-10-30T15:09:11.900651Z","ticker":"brazlian-grand-prix-winner","title":"Brazlian Grand Prix Winner","updatedAt":"2024-11-11T20:27:34.515405Z","volume":249518.857802,"volume1mo":0,"volume1wk":0,"volume1yr":0}],"featured":false,"feesEnabled":false,"funded":false,"groupItemThreshold":"7","groupItemTitle":"Sergio Perez","hasReviewedDates":true,"holdingRewardsEnabled":false,"icon":"https://polymarket-upload.s3.us-east-2.amazonaws.com/will-sergio-perez-win-the-brazilian-grand-prix-FXwb3qlN8CkX.png","id":"511396","image":"https://polymarket-upload.s3.us-east-2.amazonaws.com/will-sergio-perez-win-the-brazilian-grand-prix-FXwb3qlN8CkX.png","lastTradePrice":1,"manualActivation":false,"marketMakerAddress":"","negRisk":true,"negRiskMarketID":"0xbf55bf389f1d1c01bb07d249defdc713675daa59871da998d5b29a78ba445300","negRiskOther":false,"negRiskRequestID":"0xed3a0114771e570dc0c5ddc9c0bf13a83d7f82b91971dd1f680bbc99a0420c24","new":false,"oneDayPriceChange":0.0015,"oneHourPriceChange":0,"oneMonthPriceChange":0,"oneWeekPriceChange":0,"oneYearPriceChange":0,"orderMinSize":5,"orderPriceMinTickSize":0.001,"outcomePrices":"[\"0\", \"1\"]","outcomes":"[\"Yes\", \"No\"]","pagerDutyNotificationEnabled":false,"pendingDeployment":false,"question":"Will Sergio Perez win the Brazilian Grand Prix?","questionID":"0xbf55bf389f1d1c01bb07d249defdc713675daa59871da998d5b29a78ba445307","ready":false,"requiresTranslation":false,"resolutionSource":"","resolvedBy":"0x2F5e3684cb1F318ec51b00Edba38d79Ac2c0aA9d","restricted":true,"rewardsMaxSpread":0,"rewardsMinSize":0,"rfqEnabled":false,"seriesColor":"","showGmpOutcome":false,"showGmpSeries":false,"slug":"will-sergio-perez-win-the-brazilian-grand-prix","spread":0.008,"startDate":"2024-10-30T15:07:30.638931Z","startDateIso":"2024-10-30","submitted_by":"0x91430CaD2d3975766499717fA0D66A78D814E5c5","umaBond":"500","umaEndDate":"2024-11-11T01:56:44Z","umaResolutionStatus":"resolved","umaResolutionStatuses":"[]","umaReward":"5","updatedAt":"2024-11-11T20:27:30.261697Z","volume":"21910.242651","volume1mo":0,"volume1moAmm":0,"volume1moClob":0,"volume1wk":0,"volume1wkAmm":0,"volume1wkClob":0,"volume1yr":0,"volume1yrAmm":0,"volume1yrClob":0,"volumeClob":21910.242651,"volumeNum":21910.242651}