{"acceptingOrders":false,"acceptingOrdersTimestamp":"2024-10-10T21:52:16Z","active":true,"approved":true,"archived":false,"automaticallyActive":true,"automaticallyResolved":true,"bestAsk":1,"bestBid":0.999,"clearBookOnStart":true,"clobTokenIds":"[\"45931125495384150924233405493838684047080619965645367515077040423962126819028\", \"86691564363924594548374027840427536060811707524914143483891134876856477187700\"]","closed":true,"closedTime":"2024-10-11 23:57:48+00","conditionId":"0x94fb056710f14e9ead6e650e71ee0ee486fca66b2ec0dc5311d8d5faf179058f","createdAt":"2024-10-09T22:32:25.660902Z","cyom":false,"deploying":false,"description":"This market refers to the 2024 UEFA Nations League group stage match between Iceland and Wales scheduled for October 11, 2:45 PM ET.\n\nIf the match ends in a draw, this market will resolve to “Yes.” Otherwise, this market will resolve to “No.”\n\nIf the game is canceled or delayed beyond October 18, this market will resolve to “No.”\n\nNote: This match refers only to the outcome within the first 90 minutes of regular play plus stoppage time.","enableOrderBook":true,"endDate":"2024-10-11T12:00:00Z","endDateIso":"2024-10-11","events":[{"active":true,"archived":false,"automaticallyActive":true,"automaticallyResolved":true,"closed":true,"closedTime":"2024-10-11T23:57:48Z","commentCount":1,"createdAt":"2024-10-09T22:31:09.199043Z","creationDate":"2024-10-10T21:54:47.800353Z","cumulativeMarkets":false,"cyom":false,"deploying":false,"description":"This is a market on the outcome of the UEFA Nations League match between Iceland and Wales.","enableNegRisk":true,"enableOrderBook":true,"endDate":"2024-10-11T12:00:00Z","featured":false,"gmpChartMode":"default","icon":"https://polymarket-upload.s3.us-east-2.amazonaws.com/uefa-nations-league-iceland-vs-wales-8kZhgNFnSv6g.png","id":"13314","image":"https://polymarket-upload.s3.us-east-2.amazonaws.com/uefa-nations-league-iceland-vs-wales-8kZhgNFnSv6g.png","negRisk":true,"negRiskAugmented":false,"negRiskMarketID":"0xd430eaf0ab3276729fb6679c9994c80b4608733bb383da9dccef04f5b3fc5300","new":false,"openInterest":0,"pendingDeployment":false,"requiresTranslation":false,"restricted":true,"showAllOutcomes":true,"showMarketImages":true,"slug":"uefa-nations-league-iceland-vs-wales","startDate":"2024-10-10T21:54:47.800356Z","ticker":"uefa-nations-league-iceland-vs-wales","title":"UEFA Nations League: Iceland vs. Wales","updatedAt":"2024-10-12T22:41:03.895883Z","volume":57198.785867,"volume1mo":0,"volume1wk":0,"volume1yr":0}],"featured":false,"feesEnabled":false,"funded":false,"gameStartTime":"2024-10-11 18:45:00+00","groupItemThreshold":"2","groupItemTitle":"Draw","hasReviewedDates":true,"holdingRewardsEnabled":false,"icon":"https://polymarket-upload.s3.us-east-2.amazonaws.com/uefa-nations-league-iceland-vs-wales-8kZhgNFnSv6g.png","id":"509477","image":"https://polymarket-upload.s3.us-east-2.amazonaws.com/uefa-nations-league-iceland-vs-wales-8kZhgNFnSv6g.png","lastTradePrice":1,"manualActivation":false,"marketMakerAddress":"","negRisk":true,"negRiskMarketID":"0xd430eaf0ab3276729fb6679c9994c80b4608733bb383da9dccef04f5b3fc5300","negRiskOther":false,"negRiskRequestID":"0x3c38ecb911312308bba5eee2c0c422893002c116cb942c07eed0d50de147cdc5","new":false,"oneDayPriceChange":0.6945,"oneHourPriceChange":0,"oneMonthPriceChange":0,"oneWeekPriceChange":0,"oneYearPriceChange":0,"orderMinSize":5,"orderPriceMinTickSize":0.001,"outcomePrices":"[\"1\", \"0\"]","outcomes":"[\"Yes\", \"No\"]","pagerDutyNotificationEnabled":false,"pendingDeployment":false,"question":"Will the match between Iceland and Wales end in a draw?","questionID":"0xd430eaf0ab3276729fb6679c9994c80b4608733bb383da9dccef04f5b3fc5302","ready":false,"requiresTranslation":false,"resolutionSource":"","resolvedBy":"0x2F5e3684cb1F318ec51b00Edba38d79Ac2c0aA9d","restricted":true,"rewardsMaxSpread":0,"rewardsMinSize":0,"rfqEnabled":false,"secondsDelay":3,"seriesColor":"","slug":"will-the-match-between-iceland-and-wales-end-in-a-draw","spread":0.001,"startDate":"2024-10-10T21:53:24.28416Z","startDateIso":"2024-10-10","submitted_by":"0x91430CaD2d3975766499717fA0D66A78D814E5c5","umaBond":"500","umaEndDate":"2024-10-11T23:57:48Z","umaResolutionStatus":"resolved","umaResolutionStatuses":"[]","umaReward":"5","updatedAt":"2024-10-12T21:30:56.785723Z","volume":"13224.020031","volume1mo":0,"volume1moAmm":0,"volume1moClob":0,"volume1wk":0,"volume1wkAmm":0,"volume1wkClob":0,"volume1yr":0,"volume1yrAmm":0,"volume1yrClob":0,"volumeClob":13224.020031,"volumeNum":13224.020031}